{
  "emotion": {
    "label2idx": {
      "amusement": 0,
      "awe": 1,
      "contentment": 2,
      "excitement": 3,
      "anger": 4,
      "disgust": 5,
      "fear": 6,
      "sadness": 7
    },
    "idx2label": {
      "0": "amusement",
      "1": "awe",
      "2": "contentment",
      "3": "excitement",
      "4": "anger",
      "5": "disgust",
      "6": "fear",
      "7": "sadness"
    }
  },
  "brightness": {
    "label2idx": {
      "0.0": 0,
      "0.1": 1,
      "0.2": 2,
      "0.3": 3,
      "0.4": 4,
      "0.5": 5,
      "0.6": 6,
      "0.7": 7,
      "0.8": 8,
      "0.9": 9,
      "1.0": 10
    },
    "idx2label": {
      "0": 0.0,
      "1": 0.1,
      "2": 0.2,
      "3": 0.3,
      "4": 0.4,
      "5": 0.5,
      "6": 0.6,
      "7": 0.7,
      "8": 0.8,
      "9": 0.9,
      "10": 1.0
    }
  },
  "colorfulness": {
    "label2idx": {
      "0.0": 0,
      "0.1": 1,
      "0.2": 2,
      "0.3": 3,
      "0.4": 4,
      "0.5": 5,
      "0.6": 6,
      "0.7": 7,
      "0.8": 8,
      "0.9": 9,
      "1.0": 10
    },
    "idx2label": {
      "0": 0.0,
      "1": 0.1,
      "2": 0.2,
      "3": 0.3,
      "4": 0.4,
      "5": 0.5,
      "6": 0.6,
      "7": 0.7,
      "8": 0.8,
      "9": 0.9,
      "10": 1.0
    }
  },
  "scene": {
    "label2idx": {
      "airfield": 0,
      "airplane_cabin": 1,
      "airport_terminal": 2,
      "alley": 3,
      "amusement_park": 4,
      "apartment_building": 5,
      "aquarium": 6,
      "arcade": 7,
      "arch": 8,
      "arena": 9,
      "army_base": 10,
      "art_gallery": 11,
      "art_school": 12,
      "athletic_field": 13,
      "attic": 14,
      "auditorium": 15,
      "badlands": 16,
      "bakery/shop": 17,
      "balcony": 18,
      "ballroom": 19,
      "bamboo_forest": 20,
      "banquet_hall": 21,
      "bar": 22,
      "baseball_field": 23,
      "basement": 24,
      "basketball_court": 25,
      "bathroom": 26,
      "bazaar": 27,
      "beach": 28,
      "beach_house": 29,
      "bedroom": 30,
      "beer_hall": 31,
      "boardwalk": 32,
      "boat_deck": 33,
      "bookstore": 34,
      "booth": 35,
      "botanical_garden": 36,
      "bow_window": 37,
      "bowling_alley": 38,
      "boxing_ring": 39,
      "bridge": 40,
      "building_facade": 41,
      "bullring": 42,
      "burial_chamber": 43,
      "bus_interior": 44,
      "butchers_shop": 45,
      "butte": 46,
      "cafeteria": 47,
      "campsite": 48,
      "campus": 49,
      "canal": 50,
      "candy_store": 51,
      "canyon": 52,
      "car_interior": 53,
      "carrousel": 54,
      "castle": 55,
      "catacomb": 56,
      "cemetery": 57,
      "chalet": 58,
      "childs_room": 59,
      "church": 60,
      "classroom": 61,
      "cliff": 62,
      "clothing_store": 63,
      "coast": 64,
      "cockpit": 65,
      "coffee_shop": 66,
      "computer_room": 67,
      "conference_center": 68,
      "construction_site": 69,
      "corn_field": 70,
      "corral": 71,
      "corridor": 72,
      "cottage": 73,
      "courtyard": 74,
      "creek": 75,
      "crevasse": 76,
      "crosswalk": 77,
      "dam": 78,
      "delicatessen": 79,
      "department_store": 80,
      "desert": 81,
      "desert_road": 82,
      "dining_room": 83,
      "discotheque": 84,
      "doorway": 85,
      "dorm_room": 86,
      "downtown": 87,
      "dressing_room": 88,
      "driveway": 89,
      "elevator": 90,
      "elevator_shaft": 91,
      "entrance_hall": 92,
      "escalator": 93,
      "excavation": 94,
      "farm": 95,
      "fastfood_restaurant": 96,
      "field": 97,
      "field_road": 98,
      "fishpond": 99,
      "florist_shop": 100,
      "food_court": 101,
      "football_field": 102,
      "forest": 103,
      "forest_path": 104,
      "forest_road": 105,
      "formal_garden": 106,
      "fountain": 107,
      "garage": 108,
      "gas_station": 109,
      "gazebo": 110,
      "gift_shop": 111,
      "glacier": 112,
      "golf_course": 113,
      "greenhouse": 114,
      "grotto": 115,
      "gymnasium": 116,
      "harbor": 117,
      "hayfield": 118,
      "heliport": 119,
      "highway": 120,
      "home_office": 121,
      "home_theater": 122,
      "hospital_room": 123,
      "hot_spring": 124,
      "hotel": 125,
      "hotel_room": 126,
      "house": 127,
      "ice_cream_parlor": 128,
      "ice_floe": 129,
      "ice_shelf": 130,
      "ice_skating_rink": 131,
      "iceberg": 132,
      "industrial_area": 133,
      "islet": 134,
      "jail_cell": 135,
      "junkyard": 136,
      "kasbah": 137,
      "kennel": 138,
      "kindergarden_classroom": 139,
      "kitchen": 140,
      "lagoon": 141,
      "lake": 142,
      "landfill": 143,
      "lawn": 144,
      "lecture_room": 145,
      "library": 146,
      "lighthouse": 147,
      "lobby": 148,
      "manufactured_home": 149,
      "market": 150,
      "martial_arts_gym": 151,
      "mausoleum": 152,
      "moat": 153,
      "mosque": 154,
      "mountain": 155,
      "mountain_path": 156,
      "mountain_snowy": 157,
      "museum": 158,
      "music_studio": 159,
      "natural_history_museum": 160,
      "nursing_home": 161,
      "ocean": 162,
      "office": 163,
      "office_building": 164,
      "office_cubicles": 165,
      "operating_room": 166,
      "orchard": 167,
      "orchestra_pit": 168,
      "pagoda": 169,
      "palace": 170,
      "park": 171,
      "parking_lot": 172,
      "pasture": 173,
      "patio": 174,
      "pavilion": 175,
      "phone_booth": 176,
      "picnic_area": 177,
      "pier": 178,
      "pizzeria": 179,
      "playground": 180,
      "playroom": 181,
      "plaza": 182,
      "pond": 183,
      "porch": 184,
      "promenade": 185,
      "racecourse": 186,
      "raft": 187,
      "railroad_track": 188,
      "rainforest": 189,
      "recreation_room": 190,
      "repair_shop": 191,
      "residential_neighborhood": 192,
      "restaurant": 193,
      "rice_paddy": 194,
      "river": 195,
      "rock_arch": 196,
      "rope_bridge": 197,
      "ruin": 198,
      "runway": 199,
      "sauna": 200,
      "shed": 201,
      "shoe_shop": 202,
      "shopfront": 203,
      "shopping_mall": 204,
      "shower": 205,
      "ski_resort": 206,
      "ski_slope": 207,
      "sky": 208,
      "skyscraper": 209,
      "slum": 210,
      "snowfield": 211,
      "stable": 212,
      "stadium": 213,
      "stage": 214,
      "staircase": 215,
      "street": 216,
      "subway_station": 217,
      "supermarket": 218,
      "sushi_bar": 219,
      "swamp": 220,
      "swimming_hole": 221,
      "swimming_pool": 222,
      "synagogue": 223,
      "television_room": 224,
      "television_studio": 225,
      "temple": 226,
      "throne_room": 227,
      "topiary_garden": 228,
      "tower": 229,
      "toyshop": 230,
      "train_interior": 231,
      "train_station": 232,
      "tree_farm": 233,
      "tree_house": 234,
      "trench": 235,
      "tundra": 236,
      "underwater": 237,
      "valley": 238,
      "vegetable_garden": 239,
      "viaduct": 240,
      "village": 241,
      "vineyard": 242,
      "volcano": 243,
      "volleyball_court": 244,
      "waiting_room": 245,
      "water_park": 246,
      "waterfall": 247,
      "watering_hole": 248,
      "wave": 249,
      "wheat_field": 250,
      "wind_farm": 251,
      "windmill": 252,
      "yard": 253
    },
    "idx2label": {
      "0": "airfield",
      "1": "airplane_cabin",
      "2": "airport_terminal",
      "3": "alley",
      "4": "amusement_park",
      "5": "apartment_building",
      "6": "aquarium",
      "7": "arcade",
      "8": "arch",
      "9": "arena",
      "10": "army_base",
      "11": "art_gallery",
      "12": "art_school",
      "13": "athletic_field",
      "14": "attic",
      "15": "auditorium",
      "16": "badlands",
      "17": "bakery/shop",
      "18": "balcony",
      "19": "ballroom",
      "20": "bamboo_forest",
      "21": "banquet_hall",
      "22": "bar",
      "23": "baseball_field",
      "24": "basement",
      "25": "basketball_court",
      "26": "bathroom",
      "27": "bazaar",
      "28": "beach",
      "29": "beach_house",
      "30": "bedroom",
      "31": "beer_hall",
      "32": "boardwalk",
      "33": "boat_deck",
      "34": "bookstore",
      "35": "booth",
      "36": "botanical_garden",
      "37": "bow_window",
      "38": "bowling_alley",
      "39": "boxing_ring",
      "40": "bridge",
      "41": "building_facade",
      "42": "bullring",
      "43": "burial_chamber",
      "44": "bus_interior",
      "45": "butchers_shop",
      "46": "butte",
      "47": "cafeteria",
      "48": "campsite",
      "49": "campus",
      "50": "canal",
      "51": "candy_store",
      "52": "canyon",
      "53": "car_interior",
      "54": "carrousel",
      "55": "castle",
      "56": "catacomb",
      "57": "cemetery",
      "58": "chalet",
      "59": "childs_room",
      "60": "church",
      "61": "classroom",
      "62": "cliff",
      "63": "clothing_store",
      "64": "coast",
      "65": "cockpit",
      "66": "coffee_shop",
      "67": "computer_room",
      "68": "conference_center",
      "69": "construction_site",
      "70": "corn_field",
      "71": "corral",
      "72": "corridor",
      "73": "cottage",
      "74": "courtyard",
      "75": "creek",
      "76": "crevasse",
      "77": "crosswalk",
      "78": "dam",
      "79": "delicatessen",
      "80": "department_store",
      "81": "desert",
      "82": "desert_road",
      "83": "dining_room",
      "84": "discotheque",
      "85": "doorway",
      "86": "dorm_room",
      "87": "downtown",
      "88": "dressing_room",
      "89": "driveway",
      "90": "elevator",
      "91": "elevator_shaft",
      "92": "entrance_hall",
      "93": "escalator",
      "94": "excavation",
      "95": "farm",
      "96": "fastfood_restaurant",
      "97": "field",
      "98": "field_road",
      "99": "fishpond",
      "100": "florist_shop",
      "101": "food_court",
      "102": "football_field",
      "103": "forest",
      "104": "forest_path",
      "105": "forest_road",
      "106": "formal_garden",
      "107": "fountain",
      "108": "garage",
      "109": "gas_station",
      "110": "gazebo",
      "111": "gift_shop",
      "112": "glacier",
      "113": "golf_course",
      "114": "greenhouse",
      "115": "grotto",
      "116": "gymnasium",
      "117": "harbor",
      "118": "hayfield",
      "119": "heliport",
      "120": "highway",
      "121": "home_office",
      "122": "home_theater",
      "123": "hospital_room",
      "124": "hot_spring",
      "125": "hotel",
      "126": "hotel_room",
      "127": "house",
      "128": "ice_cream_parlor",
      "129": "ice_floe",
      "130": "ice_shelf",
      "131": "ice_skating_rink",
      "132": "iceberg",
      "133": "industrial_area",
      "134": "islet",
      "135": "jail_cell",
      "136": "junkyard",
      "137": "kasbah",
      "138": "kennel",
      "139": "kindergarden_classroom",
      "140": "kitchen",
      "141": "lagoon",
      "142": "lake",
      "143": "landfill",
      "144": "lawn",
      "145": "lecture_room",
      "146": "library",
      "147": "lighthouse",
      "148": "lobby",
      "149": "manufactured_home",
      "150": "market",
      "151": "martial_arts_gym",
      "152": "mausoleum",
      "153": "moat",
      "154": "mosque",
      "155": "mountain",
      "156": "mountain_path",
      "157": "mountain_snowy",
      "158": "museum",
      "159": "music_studio",
      "160": "natural_history_museum",
      "161": "nursing_home",
      "162": "ocean",
      "163": "office",
      "164": "office_building",
      "165": "office_cubicles",
      "166": "operating_room",
      "167": "orchard",
      "168": "orchestra_pit",
      "169": "pagoda",
      "170": "palace",
      "171": "park",
      "172": "parking_lot",
      "173": "pasture",
      "174": "patio",
      "175": "pavilion",
      "176": "phone_booth",
      "177": "picnic_area",
      "178": "pier",
      "179": "pizzeria",
      "180": "playground",
      "181": "playroom",
      "182": "plaza",
      "183": "pond",
      "184": "porch",
      "185": "promenade",
      "186": "racecourse",
      "187": "raft",
      "188": "railroad_track",
      "189": "rainforest",
      "190": "recreation_room",
      "191": "repair_shop",
      "192": "residential_neighborhood",
      "193": "restaurant",
      "194": "rice_paddy",
      "195": "river",
      "196": "rock_arch",
      "197": "rope_bridge",
      "198": "ruin",
      "199": "runway",
      "200": "sauna",
      "201": "shed",
      "202": "shoe_shop",
      "203": "shopfront",
      "204": "shopping_mall",
      "205": "shower",
      "206": "ski_resort",
      "207": "ski_slope",
      "208": "sky",
      "209": "skyscraper",
      "210": "slum",
      "211": "snowfield",
      "212": "stable",
      "213": "stadium",
      "214": "stage",
      "215": "staircase",
      "216": "street",
      "217": "subway_station",
      "218": "supermarket",
      "219": "sushi_bar",
      "220": "swamp",
      "221": "swimming_hole",
      "222": "swimming_pool",
      "223": "synagogue",
      "224": "television_room",
      "225": "television_studio",
      "226": "temple",
      "227": "throne_room",
      "228": "topiary_garden",
      "229": "tower",
      "230": "toyshop",
      "231": "train_interior",
      "232": "train_station",
      "233": "tree_farm",
      "234": "tree_house",
      "235": "trench",
      "236": "tundra",
      "237": "underwater",
      "238": "valley",
      "239": "vegetable_garden",
      "240": "viaduct",
      "241": "village",
      "242": "vineyard",
      "243": "volcano",
      "244": "volleyball_court",
      "245": "waiting_room",
      "246": "water_park",
      "247": "waterfall",
      "248": "watering_hole",
      "249": "wave",
      "250": "wheat_field",
      "251": "wind_farm",
      "252": "windmill",
      "253": "yard"
    }
  },
  "object": {
    "label2idx": {
      "Accordion": 0,
      "Airplane": 1,
      "Alarm clock": 2,
      "Alpaca": 3,
      "Animal": 4,
      "Ant": 5,
      "Antelope": 6,
      "Apple": 7,
      "Auto part": 8,
      "Axe": 9,
      "Backpack": 10,
      "Baked goods": 11,
      "Ball": 12,
      "Balloon": 13,
      "Banana": 14,
      "Barge": 15,
      "Barrel": 16,
      "Baseball bat": 17,
      "Baseball glove": 18,
      "Bat": 19,
      "Bathroom accessory": 20,
      "Bathtub": 21,
      "Bear": 22,
      "Bee": 23,
      "Beer": 24,
      "Beetle": 25,
      "Bell pepper": 26,
      "Belt": 27,
      "Bench": 28,
      "Bicycle": 29,
      "Bicycle helmet": 30,
      "Bicycle wheel": 31,
      "Billboard": 32,
      "Billiard table": 33,
      "Bird": 34,
      "Blue jay": 35,
      "Boat": 36,
      "Book": 37,
      "Bookcase": 38,
      "Boot": 39,
      "Bottle": 40,
      "Bowl": 41,
      "Bowling equipment": 42,
      "Box": 43,
      "Bread": 44,
      "Broccoli": 45,
      "Bronze sculpture": 46,
      "Brown bear": 47,
      "Building": 48,
      "Bull": 49,
      "Bus": 50,
      "Bust": 51,
      "Butterfly": 52,
      "Cabbage": 53,
      "Cake": 54,
      "Cake stand": 55,
      "Camel": 56,
      "Camera": 57,
      "Canary": 58,
      "Candle": 59,
      "Candy": 60,
      "Cannon": 61,
      "Canoe": 62,
      "Car": 63,
      "Carnivore": 64,
      "Carrot": 65,
      "Cart": 66,
      "Castle": 67,
      "Cat": 68,
      "Cat furniture": 69,
      "Caterpillar": 70,
      "Ceiling fan": 71,
      "Cello": 72,
      "Centipede": 73,
      "Chair": 74,
      "Cheetah": 75,
      "Chest of drawers": 76,
      "Chicken": 77,
      "Chopsticks": 78,
      "Christmas tree": 79,
      "Clock": 80,
      "Coat": 81,
      "Cocktail": 82,
      "Coconut": 83,
      "Coffee": 84,
      "Coffee cup": 85,
      "Coffee table": 86,
      "Coffeemaker": 87,
      "Coin": 88,
      "Computer keyboard": 89,
      "Computer monitor": 90,
      "Computer mouse": 91,
      "Convenience store": 92,
      "Cookie": 93,
      "Couch": 94,
      "Countertop": 95,
      "Cowboy hat": 96,
      "Crab": 97,
      "Crocodile": 98,
      "Croissant": 99,
      "Crown": 100,
      "Cucumber": 101,
      "Cupboard": 102,
      "Curtain": 103,
      "Dagger": 104,
      "Dairy Product": 105,
      "Deer": 106,
      "Dessert": 107,
      "Dice": 108,
      "Dinosaur": 109,
      "Dog": 110,
      "Dog bed": 111,
      "Doll": 112,
      "Dolphin": 113,
      "Door": 114,
      "Door handle": 115,
      "Doughnut": 116,
      "Dragonfly": 117,
      "Drawer": 118,
      "Drill": 119,
      "Drink": 120,
      "Drum": 121,
      "Duck": 122,
      "Eagle": 123,
      "Earrings": 124,
      "Egg": 125,
      "Elephant": 126,
      "Falcon": 127,
      "Fashion accessory": 128,
      "Fast food": 129,
      "Fedora": 130,
      "Fire hydrant": 131,
      "Fireplace": 132,
      "Fish": 133,
      "Flag": 134,
      "Flower": 135,
      "Flowerpot": 136,
      "Flute": 137,
      "Food": 138,
      "Football": 139,
      "Fork": 140,
      "Fountain": 141,
      "Fox": 142,
      "French fries": 143,
      "French horn": 144,
      "Frog": 145,
      "Fruit": 146,
      "Furniture": 147,
      "Garden Asparagus": 148,
      "Gas stove": 149,
      "Giraffe": 150,
      "Glasses": 151,
      "Glove": 152,
      "Goat": 153,
      "Goggles": 154,
      "Goldfish": 155,
      "Gondola": 156,
      "Goose": 157,
      "Grape": 158,
      "Guitar": 159,
      "Hamburger": 160,
      "Hamster": 161,
      "Handbag": 162,
      "Handgun": 163,
      "Harbor seal": 164,
      "Harp": 165,
      "Hat": 166,
      "Headphones": 167,
      "Hedgehog": 168,
      "Helicopter": 169,
      "Helmet": 170,
      "High heels": 171,
      "Hiking equipment": 172,
      "Hippopotamus": 173,
      "Home appliance": 174,
      "Horse": 175,
      "Hot dog": 176,
      "House": 177,
      "Houseplant": 178,
      "Ice cream": 179,
      "Infant bed": 180,
      "Insect": 181,
      "Invertebrate": 182,
      "Isopod": 183,
      "Jacket": 184,
      "Jaguar": 185,
      "Jeans": 186,
      "Jet ski": 187,
      "Juice": 188,
      "Kangaroo": 189,
      "Kettle": 190,
      "Kitchen & dining room table": 191,
      "Kitchen appliance": 192,
      "Kite": 193,
      "Knife": 194,
      "Ladder": 195,
      "Ladybug": 196,
      "Lamp": 197,
      "Land vehicle": 198,
      "Lantern": 199,
      "Laptop": 200,
      "Lavender": 201,
      "Lemon": 202,
      "Leopard": 203,
      "Light bulb": 204,
      "Light switch": 205,
      "Lighthouse": 206,
      "Lily": 207,
      "Lion": 208,
      "Lizard": 209,
      "Lobster": 210,
      "Loveseat": 211,
      "Luggage and bags": 212,
      "Lynx": 213,
      "Magpie": 214,
      "Mammal": 215,
      "Mango": 216,
      "Maple": 217,
      "Marine invertebrates": 218,
      "Marine mammal": 219,
      "Mechanical fan": 220,
      "Medical equipment": 221,
      "Microphone": 222,
      "Miniskirt": 223,
      "Mirror": 224,
      "Mixing bowl": 225,
      "Mobile phone": 226,
      "Monkey": 227,
      "Moths and butterflies": 228,
      "Motorcycle": 229,
      "Mouse": 230,
      "Muffin": 231,
      "Mug": 232,
      "Mule": 233,
      "Mushroom": 234,
      "Musical instrument": 235,
      "Musical keyboard": 236,
      "Necklace": 237,
      "Nightstand": 238,
      "Office supplies": 239,
      "Orange": 240,
      "Organ": 241,
      "Ostrich": 242,
      "Otter": 243,
      "Oven": 244,
      "Owl": 245,
      "Oyster": 246,
      "Paddle": 247,
      "Palm tree": 248,
      "Pancake": 249,
      "Panda": 250,
      "Parachute": 251,
      "Parrot": 252,
      "Pasta": 253,
      "Pastry": 254,
      "Peach": 255,
      "Pear": 256,
      "Pen": 257,
      "Penguin": 258,
      "Personal flotation device": 259,
      "Piano": 260,
      "Picnic basket": 261,
      "Picture frame": 262,
      "Pig": 263,
      "Pillow": 264,
      "Pineapple": 265,
      "Pizza": 266,
      "Plant": 267,
      "Plastic bag": 268,
      "Plate": 269,
      "Plumbing fixture": 270,
      "Polar bear": 271,
      "Popcorn": 272,
      "Porch": 273,
      "Poster": 274,
      "Potato": 275,
      "Pumpkin": 276,
      "Rabbit": 277,
      "Raccoon": 278,
      "Racket": 279,
      "Raven": 280,
      "Red panda": 281,
      "Refrigerator": 282,
      "Reptile": 283,
      "Rhinoceros": 284,
      "Rifle": 285,
      "Roller skates": 286,
      "Rose": 287,
      "Rugby ball": 288,
      "Ruler": 289,
      "Salad": 290,
      "Sandal": 291,
      "Sandwich": 292,
      "Saucer": 293,
      "Saxophone": 294,
      "Scarf": 295,
      "Scissors": 296,
      "Scorpion": 297,
      "Sculpture": 298,
      "Sea lion": 299,
      "Sea turtle": 300,
      "Seafood": 301,
      "Segway": 302,
      "Sheep": 303,
      "Shelf": 304,
      "Shellfish": 305,
      "Shirt": 306,
      "Shorts": 307,
      "Shotgun": 308,
      "Shrimp": 309,
      "Sink": 310,
      "Skateboard": 311,
      "Ski": 312,
      "Skirt": 313,
      "Skull": 314,
      "Skyscraper": 315,
      "Slow cooker": 316,
      "Snack": 317,
      "Snail": 318,
      "Snake": 319,
      "Snowboard": 320,
      "Snowman": 321,
      "Snowmobile": 322,
      "Sock": 323,
      "Sofa bed": 324,
      "Sombrero": 325,
      "Sparrow": 326,
      "Spider": 327,
      "Spoon": 328,
      "Sports equipment": 329,
      "Sports uniform": 330,
      "Squirrel": 331,
      "Stairs": 332,
      "Starfish": 333,
      "Stop sign": 334,
      "Strawberry": 335,
      "Street light": 336,
      "Suit": 337,
      "Suitcase": 338,
      "Sun hat": 339,
      "Sunflower": 340,
      "Sunglasses": 341,
      "Surfboard": 342,
      "Sushi": 343,
      "Swan": 344,
      "Swim cap": 345,
      "Swimming pool": 346,
      "Swimwear": 347,
      "Table": 348,
      "Table tennis racket": 349,
      "Tablet computer": 350,
      "Tableware": 351,
      "Tap": 352,
      "Taxi": 353,
      "Tea": 354,
      "Teapot": 355,
      "Teddy bear": 356,
      "Television": 357,
      "Tennis ball": 358,
      "Tennis racket": 359,
      "Tent": 360,
      "Tiara": 361,
      "Tie": 362,
      "Tiger": 363,
      "Tin can": 364,
      "Toilet": 365,
      "Tomato": 366,
      "Tool": 367,
      "Tortoise": 368,
      "Tower": 369,
      "Toy": 370,
      "Traffic light": 371,
      "Traffic sign": 372,
      "Train": 373,
      "Tree": 374,
      "Tripod": 375,
      "Trombone": 376,
      "Trousers": 377,
      "Truck": 378,
      "Trumpet": 379,
      "Turkey": 380,
      "Umbrella": 381,
      "Unicycle": 382,
      "Van": 383,
      "Vase": 384,
      "Vegetable": 385,
      "Vehicle registration plate": 386,
      "Violin": 387,
      "Volleyball": 388,
      "Wall clock": 389,
      "Wardrobe": 390,
      "Washing machine": 391,
      "Waste container": 392,
      "Watch": 393,
      "Watermelon": 394,
      "Weapon": 395,
      "Whale": 396,
      "Wheel": 397,
      "Wheelchair": 398,
      "Willow": 399,
      "Window": 400,
      "Window blind": 401,
      "Wine": 402,
      "Wine glass": 403,
      "Wine rack": 404,
      "Wok": 405,
      "Woodpecker": 406,
      "Worm": 407,
      "Zebra": 408
    },
    "idx2label": {
      "0": "Accordion",
      "1": "Airplane",
      "2": "Alarm clock",
      "3": "Alpaca",
      "4": "Animal",
      "5": "Ant",
      "6": "Antelope",
      "7": "Apple",
      "8": "Auto part",
      "9": "Axe",
      "10": "Backpack",
      "11": "Baked goods",
      "12": "Ball",
      "13": "Balloon",
      "14": "Banana",
      "15": "Barge",
      "16": "Barrel",
      "17": "Baseball bat",
      "18": "Baseball glove",
      "19": "Bat",
      "20": "Bathroom accessory",
      "21": "Bathtub",
      "22": "Bear",
      "23": "Bee",
      "24": "Beer",
      "25": "Beetle",
      "26": "Bell pepper",
      "27": "Belt",
      "28": "Bench",
      "29": "Bicycle",
      "30": "Bicycle helmet",
      "31": "Bicycle wheel",
      "32": "Billboard",
      "33": "Billiard table",
      "34": "Bird",
      "35": "Blue jay",
      "36": "Boat",
      "37": "Book",
      "38": "Bookcase",
      "39": "Boot",
      "40": "Bottle",
      "41": "Bowl",
      "42": "Bowling equipment",
      "43": "Box",
      "44": "Bread",
      "45": "Broccoli",
      "46": "Bronze sculpture",
      "47": "Brown bear",
      "48": "Building",
      "49": "Bull",
      "50": "Bus",
      "51": "Bust",
      "52": "Butterfly",
      "53": "Cabbage",
      "54": "Cake",
      "55": "Cake stand",
      "56": "Camel",
      "57": "Camera",
      "58": "Canary",
      "59": "Candle",
      "60": "Candy",
      "61": "Cannon",
      "62": "Canoe",
      "63": "Car",
      "64": "Carnivore",
      "65": "Carrot",
      "66": "Cart",
      "67": "Castle",
      "68": "Cat",
      "69": "Cat furniture",
      "70": "Caterpillar",
      "71": "Ceiling fan",
      "72": "Cello",
      "73": "Centipede",
      "74": "Chair",
      "75": "Cheetah",
      "76": "Chest of drawers",
      "77": "Chicken",
      "78": "Chopsticks",
      "79": "Christmas tree",
      "80": "Clock",
      "81": "Coat",
      "82": "Cocktail",
      "83": "Coconut",
      "84": "Coffee",
      "85": "Coffee cup",
      "86": "Coffee table",
      "87": "Coffeemaker",
      "88": "Coin",
      "89": "Computer keyboard",
      "90": "Computer monitor",
      "91": "Computer mouse",
      "92": "Convenience store",
      "93": "Cookie",
      "94": "Couch",
      "95": "Countertop",
      "96": "Cowboy hat",
      "97": "Crab",
      "98": "Crocodile",
      "99": "Croissant",
      "100": "Crown",
      "101": "Cucumber",
      "102": "Cupboard",
      "103": "Curtain",
      "104": "Dagger",
      "105": "Dairy Product",
      "106": "Deer",
      "107": "Dessert",
      "108": "Dice",
      "109": "Dinosaur",
      "110": "Dog",
      "111": "Dog bed",
      "112": "Doll",
      "113": "Dolphin",
      "114": "Door",
      "115": "Door handle",
      "116": "Doughnut",
      "117": "Dragonfly",
      "118": "Drawer",
      "119": "Drill",
      "120": "Drink",
      "121": "Drum",
      "122": "Duck",
      "123": "Eagle",
      "124": "Earrings",
      "125": "Egg",
      "126": "Elephant",
      "127": "Falcon",
      "128": "Fashion accessory",
      "129": "Fast food",
      "130": "Fedora",
      "131": "Fire hydrant",
      "132": "Fireplace",
      "133": "Fish",
      "134": "Flag",
      "135": "Flower",
      "136": "Flowerpot",
      "137": "Flute",
      "138": "Food",
      "139": "Football",
      "140": "Fork",
      "141": "Fountain",
      "142": "Fox",
      "143": "French fries",
      "144": "French horn",
      "145": "Frog",
      "146": "Fruit",
      "147": "Furniture",
      "148": "Garden Asparagus",
      "149": "Gas stove",
      "150": "Giraffe",
      "151": "Glasses",
      "152": "Glove",
      "153": "Goat",
      "154": "Goggles",
      "155": "Goldfish",
      "156": "Gondola",
      "157": "Goose",
      "158": "Grape",
      "159": "Guitar",
      "160": "Hamburger",
      "161": "Hamster",
      "162": "Handbag",
      "163": "Handgun",
      "164": "Harbor seal",
      "165": "Harp",
      "166": "Hat",
      "167": "Headphones",
      "168": "Hedgehog",
      "169": "Helicopter",
      "170": "Helmet",
      "171": "High heels",
      "172": "Hiking equipment",
      "173": "Hippopotamus",
      "174": "Home appliance",
      "175": "Horse",
      "176": "Hot dog",
      "177": "House",
      "178": "Houseplant",
      "179": "Ice cream",
      "180": "Infant bed",
      "181": "Insect",
      "182": "Invertebrate",
      "183": "Isopod",
      "184": "Jacket",
      "185": "Jaguar",
      "186": "Jeans",
      "187": "Jet ski",
      "188": "Juice",
      "189": "Kangaroo",
      "190": "Kettle",
      "191": "Kitchen & dining room table",
      "192": "Kitchen appliance",
      "193": "Kite",
      "194": "Knife",
      "195": "Ladder",
      "196": "Ladybug",
      "197": "Lamp",
      "198": "Land vehicle",
      "199": "Lantern",
      "200": "Laptop",
      "201": "Lavender",
      "202": "Lemon",
      "203": "Leopard",
      "204": "Light bulb",
      "205": "Light switch",
      "206": "Lighthouse",
      "207": "Lily",
      "208": "Lion",
      "209": "Lizard",
      "210": "Lobster",
      "211": "Loveseat",
      "212": "Luggage and bags",
      "213": "Lynx",
      "214": "Magpie",
      "215": "Mammal",
      "216": "Mango",
      "217": "Maple",
      "218": "Marine invertebrates",
      "219": "Marine mammal",
      "220": "Mechanical fan",
      "221": "Medical equipment",
      "222": "Microphone",
      "223": "Miniskirt",
      "224": "Mirror",
      "225": "Mixing bowl",
      "226": "Mobile phone",
      "227": "Monkey",
      "228": "Moths and butterflies",
      "229": "Motorcycle",
      "230": "Mouse",
      "231": "Muffin",
      "232": "Mug",
      "233": "Mule",
      "234": "Mushroom",
      "235": "Musical instrument",
      "236": "Musical keyboard",
      "237": "Necklace",
      "238": "Nightstand",
      "239": "Office supplies",
      "240": "Orange",
      "241": "Organ",
      "242": "Ostrich",
      "243": "Otter",
      "244": "Oven",
      "245": "Owl",
      "246": "Oyster",
      "247": "Paddle",
      "248": "Palm tree",
      "249": "Pancake",
      "250": "Panda",
      "251": "Parachute",
      "252": "Parrot",
      "253": "Pasta",
      "254": "Pastry",
      "255": "Peach",
      "256": "Pear",
      "257": "Pen",
      "258": "Penguin",
      "259": "Personal flotation device",
      "260": "Piano",
      "261": "Picnic basket",
      "262": "Picture frame",
      "263": "Pig",
      "264": "Pillow",
      "265": "Pineapple",
      "266": "Pizza",
      "267": "Plant",
      "268": "Plastic bag",
      "269": "Plate",
      "270": "Plumbing fixture",
      "271": "Polar bear",
      "272": "Popcorn",
      "273": "Porch",
      "274": "Poster",
      "275": "Potato",
      "276": "Pumpkin",
      "277": "Rabbit",
      "278": "Raccoon",
      "279": "Racket",
      "280": "Raven",
      "281": "Red panda",
      "282": "Refrigerator",
      "283": "Reptile",
      "284": "Rhinoceros",
      "285": "Rifle",
      "286": "Roller skates",
      "287": "Rose",
      "288": "Rugby ball",
      "289": "Ruler",
      "290": "Salad",
      "291": "Sandal",
      "292": "Sandwich",
      "293": "Saucer",
      "294": "Saxophone",
      "295": "Scarf",
      "296": "Scissors",
      "297": "Scorpion",
      "298": "Sculpture",
      "299": "Sea lion",
      "300": "Sea turtle",
      "301": "Seafood",
      "302": "Segway",
      "303": "Sheep",
      "304": "Shelf",
      "305": "Shellfish",
      "306": "Shirt",
      "307": "Shorts",
      "308": "Shotgun",
      "309": "Shrimp",
      "310": "Sink",
      "311": "Skateboard",
      "312": "Ski",
      "313": "Skirt",
      "314": "Skull",
      "315": "Skyscraper",
      "316": "Slow cooker",
      "317": "Snack",
      "318": "Snail",
      "319": "Snake",
      "320": "Snowboard",
      "321": "Snowman",
      "322": "Snowmobile",
      "323": "Sock",
      "324": "Sofa bed",
      "325": "Sombrero",
      "326": "Sparrow",
      "327": "Spider",
      "328": "Spoon",
      "329": "Sports equipment",
      "330": "Sports uniform",
      "331": "Squirrel",
      "332": "Stairs",
      "333": "Starfish",
      "334": "Stop sign",
      "335": "Strawberry",
      "336": "Street light",
      "337": "Suit",
      "338": "Suitcase",
      "339": "Sun hat",
      "340": "Sunflower",
      "341": "Sunglasses",
      "342": "Surfboard",
      "343": "Sushi",
      "344": "Swan",
      "345": "Swim cap",
      "346": "Swimming pool",
      "347": "Swimwear",
      "348": "Table",
      "349": "Table tennis racket",
      "350": "Tablet computer",
      "351": "Tableware",
      "352": "Tap",
      "353": "Taxi",
      "354": "Tea",
      "355": "Teapot",
      "356": "Teddy bear",
      "357": "Television",
      "358": "Tennis ball",
      "359": "Tennis racket",
      "360": "Tent",
      "361": "Tiara",
      "362": "Tie",
      "363": "Tiger",
      "364": "Tin can",
      "365": "Toilet",
      "366": "Tomato",
      "367": "Tool",
      "368": "Tortoise",
      "369": "Tower",
      "370": "Toy",
      "371": "Traffic light",
      "372": "Traffic sign",
      "373": "Train",
      "374": "Tree",
      "375": "Tripod",
      "376": "Trombone",
      "377": "Trousers",
      "378": "Truck",
      "379": "Trumpet",
      "380": "Turkey",
      "381": "Umbrella",
      "382": "Unicycle",
      "383": "Van",
      "384": "Vase",
      "385": "Vegetable",
      "386": "Vehicle registration plate",
      "387": "Violin",
      "388": "Volleyball",
      "389": "Wall clock",
      "390": "Wardrobe",
      "391": "Washing machine",
      "392": "Waste container",
      "393": "Watch",
      "394": "Watermelon",
      "395": "Weapon",
      "396": "Whale",
      "397": "Wheel",
      "398": "Wheelchair",
      "399": "Willow",
      "400": "Window",
      "401": "Window blind",
      "402": "Wine",
      "403": "Wine glass",
      "404": "Wine rack",
      "405": "Wok",
      "406": "Woodpecker",
      "407": "Worm",
      "408": "Zebra"
    }
  },
  "facial_expression": {
    "label2idx": {
      "angry": 0,
      "disgust": 1,
      "fear": 2,
      "happy": 3,
      "sad": 4,
      "surprise": 5
    },
    "idx2label": {
      "0": "angry",
      "1": "disgust",
      "2": "fear",
      "3": "happy",
      "4": "sad",
      "5": "surprise"
    }
  },
  "human_action": {
    "label2idx": {
      "abseiling": 0,
      "answering questions": 1,
      "applauding": 2,
      "applying cream": 3,
      "archery": 4,
      "arm wrestling": 5,
      "arranging flowers": 6,
      "baby waking up": 7,
      "baking cookies": 8,
      "balloon blowing": 9,
      "bandaging": 10,
      "barbequing": 11,
      "bartending": 12,
      "belly dancing": 13,
      "bending back": 14,
      "bending metal": 15,
      "biking through snow": 16,
      "blowing leaves": 17,
      "blowing nose": 18,
      "blowing out candles": 19,
      "bouncing on trampoline": 20,
      "bowling": 21,
      "boxing ": 22,
      "braiding hair": 23,
      "brush painting": 24,
      "brushing hair": 25,
      "brushing teeth": 26,
      "bungee jumping": 27,
      "busking": 28,
      "canoeing or kayaking": 29,
      "carrying baby": 30,
      "cartwheeling": 31,
      "carving pumpkin": 32,
      "catching fish": 33,
      "catching or throwing baseball": 34,
      "catching or throwing frisbee": 35,
      "celebrating": 36,
      "changing wheel": 37,
      "cheerleading": 38,
      "clapping": 39,
      "clay pottery making": 40,
      "cleaning toilet": 41,
      "climbing a rope": 42,
      "climbing ladder": 43,
      "climbing tree": 44,
      "contact juggling": 45,
      "cooking egg": 46,
      "cooking on campfire": 47,
      "counting money": 48,
      "crawling baby": 49,
      "crossing river": 50,
      "crying": 51,
      "curling hair": 52,
      "cutting nails": 53,
      "cutting pineapple": 54,
      "cutting watermelon": 55,
      "dancing": 56,
      "dancing ballet": 57,
      "decorating the christmas tree": 58,
      "digging": 59,
      "dining": 60,
      "diving cliff": 61,
      "doing aerobics": 62,
      "doing laundry": 63,
      "drawing": 64,
      "dribbling basketball": 65,
      "drinking": 66,
      "drinking beer": 67,
      "drinking shots": 68,
      "driving car": 69,
      "driving tractor": 70,
      "drop kicking": 71,
      "dunking basketball": 72,
      "eating burger": 73,
      "eating cake": 74,
      "eating carrots": 75,
      "eating chips": 76,
      "eating doughnuts": 77,
      "eating hotdog": 78,
      "eating ice cream": 79,
      "eating spaghetti": 80,
      "eating watermelon": 81,
      "exercising arm": 82,
      "exercising with an exercise ball": 83,
      "extinguishing fire": 84,
      "feeding birds": 85,
      "feeding fish": 86,
      "feeding goats": 87,
      "finger snapping": 88,
      "fixing hair": 89,
      "flying kite": 90,
      "folding paper": 91,
      "garbage collecting": 92,
      "getting a haircut": 93,
      "getting a tattoo": 94,
      "giving or receiving award": 95,
      "gymnastics tumbling": 96,
      "headbanging": 97,
      "headbutting": 98,
      "high kick": 99,
      "hitting baseball": 100,
      "holding snake": 101,
      "hugging": 102,
      "hula hooping": 103,
      "ice climbing": 104,
      "ice fishing": 105,
      "ice skating": 106,
      "jetskiing": 107,
      "jogging": 108,
      "juggling balls": 109,
      "juggling fire": 110,
      "juggling soccer ball": 111,
      "jumping into pool": 112,
      "jumpstyle dancing": 113,
      "kicking field goal": 114,
      "kicking soccer ball": 115,
      "kissing": 116,
      "kitesurfing": 117,
      "knitting": 118,
      "laughing": 119,
      "lunge": 120,
      "making a cake": 121,
      "making a sandwich": 122,
      "making bed": 123,
      "making pizza": 124,
      "making snowman": 125,
      "making tea": 126,
      "marching": 127,
      "massaging back": 128,
      "massaging feet": 129,
      "massaging person's head": 130,
      "motorcycling": 131,
      "moving furniture": 132,
      "opening bottle": 133,
      "opening present": 134,
      "paragliding": 135,
      "petting animal (not cat)": 136,
      "petting cat": 137,
      "picking fruit": 138,
      "playing accordion": 139,
      "playing badminton": 140,
      "playing bagpipes": 141,
      "playing basketball": 142,
      "playing bass guitar": 143,
      "playing cards": 144,
      "playing cello": 145,
      "playing chess": 146,
      "playing cricket": 147,
      "playing cymbals": 148,
      "playing drums": 149,
      "playing flute": 150,
      "playing golf": 151,
      "playing guitar": 152,
      "playing harmonica": 153,
      "playing hockey": 154,
      "playing ice hockey": 155,
      "playing keyboard": 156,
      "playing kickball": 157,
      "playing piano": 158,
      "playing poker": 159,
      "playing saxophone": 160,
      "playing tennis": 161,
      "playing trombone": 162,
      "playing trumpet": 163,
      "playing ukulele": 164,
      "playing violin": 165,
      "playing volleyball": 166,
      "pull ups": 167,
      "pumping fist": 168,
      "punching bag": 169,
      "push up": 170,
      "pushing car": 171,
      "pushing cart": 172,
      "pushing wheelchair": 173,
      "reading book": 174,
      "reading newspaper": 175,
      "recording music": 176,
      "riding a bike": 177,
      "riding camel": 178,
      "riding elephant": 179,
      "riding mechanical bull": 180,
      "riding mountain bike": 181,
      "riding mule": 182,
      "riding or walking with horse": 183,
      "riding scooter": 184,
      "riding unicycle": 185,
      "rock climbing": 186,
      "rock scissors paper": 187,
      "roller skating": 188,
      "sailing": 189,
      "scuba diving": 190,
      "shaking hands": 191,
      "shaking head": 192,
      "shooting basketball": 193,
      "shooting goal (soccer)": 194,
      "shoveling snow": 195,
      "side kick": 196,
      "singing": 197,
      "situp": 198,
      "skateboarding": 199,
      "skiing": 200,
      "skydiving": 201,
      "slacklining": 202,
      "slapping": 203,
      "sled dog racing": 204,
      "smoking": 205,
      "smoking hookah": 206,
      "sniffing": 207,
      "snorkeling": 208,
      "snowboarding": 209,
      "snowkiting": 210,
      "snowmobiling": 211,
      "somersaulting": 212,
      "spraying": 213,
      "squat": 214,
      "sticking tongue out": 215,
      "stretching arm": 216,
      "stretching leg": 217,
      "strumming guitar": 218,
      "surfing crowd": 219,
      "surfing water": 220,
      "sweeping floor": 221,
      "swimming backstroke": 222,
      "swimming breast stroke": 223,
      "swimming butterfly stroke": 224,
      "swing dancing": 225,
      "swinging legs": 226,
      "swinging on something": 227,
      "sword fighting": 228,
      "tai chi": 229,
      "taking a shower": 230,
      "tapping guitar": 231,
      "tasting beer": 232,
      "tasting food": 233,
      "texting": 234,
      "throwing axe": 235,
      "throwing ball": 236,
      "tobogganing": 237,
      "tossing salad": 238,
      "training dog": 239,
      "trimming or shaving beard": 240,
      "tying bow tie": 241,
      "tying tie": 242,
      "unloading truck": 243,
      "using computer": 244,
      "using remote controller (not gaming)": 245,
      "using segway": 246,
      "waiting in line": 247,
      "walking the dog": 248,
      "washing dishes": 249,
      "washing feet": 250,
      "washing hair": 251,
      "washing hands": 252,
      "water skiing": 253,
      "water sliding": 254,
      "watering plants": 255,
      "welding": 256,
      "whistling": 257,
      "windsurfing": 258,
      "wrapping present": 259,
      "wrestling": 260,
      "writing": 261,
      "yawning": 262,
      "yoga": 263
    },
    "idx2label": {
      "0": "abseiling",
      "1": "answering questions",
      "2": "applauding",
      "3": "applying cream",
      "4": "archery",
      "5": "arm wrestling",
      "6": "arranging flowers",
      "7": "baby waking up",
      "8": "baking cookies",
      "9": "balloon blowing",
      "10": "bandaging",
      "11": "barbequing",
      "12": "bartending",
      "13": "belly dancing",
      "14": "bending back",
      "15": "bending metal",
      "16": "biking through snow",
      "17": "blowing leaves",
      "18": "blowing nose",
      "19": "blowing out candles",
      "20": "bouncing on trampoline",
      "21": "bowling",
      "22": "boxing ",
      "23": "braiding hair",
      "24": "brush painting",
      "25": "brushing hair",
      "26": "brushing teeth",
      "27": "bungee jumping",
      "28": "busking",
      "29": "canoeing or kayaking",
      "30": "carrying baby",
      "31": "cartwheeling",
      "32": "carving pumpkin",
      "33": "catching fish",
      "34": "catching or throwing baseball",
      "35": "catching or throwing frisbee",
      "36": "celebrating",
      "37": "changing wheel",
      "38": "cheerleading",
      "39": "clapping",
      "40": "clay pottery making",
      "41": "cleaning toilet",
      "42": "climbing a rope",
      "43": "climbing ladder",
      "44": "climbing tree",
      "45": "contact juggling",
      "46": "cooking egg",
      "47": "cooking on campfire",
      "48": "counting money",
      "49": "crawling baby",
      "50": "crossing river",
      "51": "crying",
      "52": "curling hair",
      "53": "cutting nails",
      "54": "cutting pineapple",
      "55": "cutting watermelon",
      "56": "dancing",
      "57": "dancing ballet",
      "58": "decorating the christmas tree",
      "59": "digging",
      "60": "dining",
      "61": "diving cliff",
      "62": "doing aerobics",
      "63": "doing laundry",
      "64": "drawing",
      "65": "dribbling basketball",
      "66": "drinking",
      "67": "drinking beer",
      "68": "drinking shots",
      "69": "driving car",
      "70": "driving tractor",
      "71": "drop kicking",
      "72": "dunking basketball",
      "73": "eating burger",
      "74": "eating cake",
      "75": "eating carrots",
      "76": "eating chips",
      "77": "eating doughnuts",
      "78": "eating hotdog",
      "79": "eating ice cream",
      "80": "eating spaghetti",
      "81": "eating watermelon",
      "82": "exercising arm",
      "83": "exercising with an exercise ball",
      "84": "extinguishing fire",
      "85": "feeding birds",
      "86": "feeding fish",
      "87": "feeding goats",
      "88": "finger snapping",
      "89": "fixing hair",
      "90": "flying kite",
      "91": "folding paper",
      "92": "garbage collecting",
      "93": "getting a haircut",
      "94": "getting a tattoo",
      "95": "giving or receiving award",
      "96": "gymnastics tumbling",
      "97": "headbanging",
      "98": "headbutting",
      "99": "high kick",
      "100": "hitting baseball",
      "101": "holding snake",
      "102": "hugging",
      "103": "hula hooping",
      "104": "ice climbing",
      "105": "ice fishing",
      "106": "ice skating",
      "107": "jetskiing",
      "108": "jogging",
      "109": "juggling balls",
      "110": "juggling fire",
      "111": "juggling soccer ball",
      "112": "jumping into pool",
      "113": "jumpstyle dancing",
      "114": "kicking field goal",
      "115": "kicking soccer ball",
      "116": "kissing",
      "117": "kitesurfing",
      "118": "knitting",
      "119": "laughing",
      "120": "lunge",
      "121": "making a cake",
      "122": "making a sandwich",
      "123": "making bed",
      "124": "making pizza",
      "125": "making snowman",
      "126": "making tea",
      "127": "marching",
      "128": "massaging back",
      "129": "massaging feet",
      "130": "massaging person's head",
      "131": "motorcycling",
      "132": "moving furniture",
      "133": "opening bottle",
      "134": "opening present",
      "135": "paragliding",
      "136": "petting animal (not cat)",
      "137": "petting cat",
      "138": "picking fruit",
      "139": "playing accordion",
      "140": "playing badminton",
      "141": "playing bagpipes",
      "142": "playing basketball",
      "143": "playing bass guitar",
      "144": "playing cards",
      "145": "playing cello",
      "146": "playing chess",
      "147": "playing cricket",
      "148": "playing cymbals",
      "149": "playing drums",
      "150": "playing flute",
      "151": "playing golf",
      "152": "playing guitar",
      "153": "playing harmonica",
      "154": "playing hockey",
      "155": "playing ice hockey",
      "156": "playing keyboard",
      "157": "playing kickball",
      "158": "playing piano",
      "159": "playing poker",
      "160": "playing saxophone",
      "161": "playing tennis",
      "162": "playing trombone",
      "163": "playing trumpet",
      "164": "playing ukulele",
      "165": "playing violin",
      "166": "playing volleyball",
      "167": "pull ups",
      "168": "pumping fist",
      "169": "punching bag",
      "170": "push up",
      "171": "pushing car",
      "172": "pushing cart",
      "173": "pushing wheelchair",
      "174": "reading book",
      "175": "reading newspaper",
      "176": "recording music",
      "177": "riding a bike",
      "178": "riding camel",
      "179": "riding elephant",
      "180": "riding mechanical bull",
      "181": "riding mountain bike",
      "182": "riding mule",
      "183": "riding or walking with horse",
      "184": "riding scooter",
      "185": "riding unicycle",
      "186": "rock climbing",
      "187": "rock scissors paper",
      "188": "roller skating",
      "189": "sailing",
      "190": "scuba diving",
      "191": "shaking hands",
      "192": "shaking head",
      "193": "shooting basketball",
      "194": "shooting goal (soccer)",
      "195": "shoveling snow",
      "196": "side kick",
      "197": "singing",
      "198": "situp",
      "199": "skateboarding",
      "200": "skiing",
      "201": "skydiving",
      "202": "slacklining",
      "203": "slapping",
      "204": "sled dog racing",
      "205": "smoking",
      "206": "smoking hookah",
      "207": "sniffing",
      "208": "snorkeling",
      "209": "snowboarding",
      "210": "snowkiting",
      "211": "snowmobiling",
      "212": "somersaulting",
      "213": "spraying",
      "214": "squat",
      "215": "sticking tongue out",
      "216": "stretching arm",
      "217": "stretching leg",
      "218": "strumming guitar",
      "219": "surfing crowd",
      "220": "surfing water",
      "221": "sweeping floor",
      "222": "swimming backstroke",
      "223": "swimming breast stroke",
      "224": "swimming butterfly stroke",
      "225": "swing dancing",
      "226": "swinging legs",
      "227": "swinging on something",
      "228": "sword fighting",
      "229": "tai chi",
      "230": "taking a shower",
      "231": "tapping guitar",
      "232": "tasting beer",
      "233": "tasting food",
      "234": "texting",
      "235": "throwing axe",
      "236": "throwing ball",
      "237": "tobogganing",
      "238": "tossing salad",
      "239": "training dog",
      "240": "trimming or shaving beard",
      "241": "tying bow tie",
      "242": "tying tie",
      "243": "unloading truck",
      "244": "using computer",
      "245": "using remote controller (not gaming)",
      "246": "using segway",
      "247": "waiting in line",
      "248": "walking the dog",
      "249": "washing dishes",
      "250": "washing feet",
      "251": "washing hair",
      "252": "washing hands",
      "253": "water skiing",
      "254": "water sliding",
      "255": "watering plants",
      "256": "welding",
      "257": "whistling",
      "258": "windsurfing",
      "259": "wrapping present",
      "260": "wrestling",
      "261": "writing",
      "262": "yawning",
      "263": "yoga"
    }
  }
}